distributor/__init__.py
distributor/templates/NIC.html
distributor/templates/_table.html
distributor/templates/index.html
distributor/templates/web.html
distributor-2.4.1.data/scripts/distributor-gen
distributor-2.4.1.dist-info/top_level.txt
distributor-2.4.1.dist-info/METADATA
distributor-2.4.1.dist-info/DESCRIPTION.rst
distributor-2.4.1.dist-info/metadata.json
distributor-2.4.1.dist-info/WHEEL
distributor-2.4.1.dist-info/RECORD
