Metadata-Version: 2.0
Name: distributor
Version: 2.4.1
Summary: Nginx, Haproxy configs and DNS analyzer.
Home-page: https://github.com/m-messiah/distributor
Author: m_messiah
Author-email: m.muzafarov@gmail.com
License: MIT
Keywords: haproxy nginx bind nic.ru
Platform: UNKNOWN
Classifier: Development Status :: 5 - Production/Stable
Classifier: Intended Audience :: System Administrators
Classifier: Topic :: Utilities
Classifier: License :: OSI Approved :: MIT License
Classifier: Programming Language :: Python :: 2
Classifier: Programming Language :: Python :: 2.7
Classifier: Programming Language :: Python :: 3
Classifier: Programming Language :: Python :: 3.2
Classifier: Programming Language :: Python :: 3.3
Classifier: Programming Language :: Python :: 3.4
Classifier: Programming Language :: Python :: 3.5
Requires-Dist: jinja2
Requires-Dist: pyparsing
Requires-Dist: dnspython
Requires-Dist: requests
